arzule_ingest/__init__.py
arzule_ingest/audit.py
arzule_ingest/cli.py
arzule_ingest/config.py
arzule_ingest/endpoints.py
arzule_ingest/ids.py
arzule_ingest/logger.py
arzule_ingest/mode.py
arzule_ingest/run.py
arzule_ingest/sanitize.py
arzule_ingest/autogen/__init__.py
arzule_ingest/autogen/handoff.py
arzule_ingest/autogen/hooks.py
arzule_ingest/autogen/install.py
arzule_ingest/autogen/normalize.py
arzule_ingest/autogen/spanctx.py
arzule_ingest/autogen_v2/__init__.py
arzule_ingest/autogen_v2/hooks.py
arzule_ingest/autogen_v2/install.py
arzule_ingest/autogen_v2/normalize.py
arzule_ingest/autogen_v2/spanctx.py
arzule_ingest/autogen_v2/telemetry.py
arzule_ingest/blobs/__init__.py
arzule_ingest/blobs/base.py
arzule_ingest/blobs/http_blob.py
arzule_ingest/blobs/inline.py
arzule_ingest/claude/__init__.py
arzule_ingest/claude/__main__.py
arzule_ingest/claude/handoff.py
arzule_ingest/claude/hook.py
arzule_ingest/claude/hook_cli.py
arzule_ingest/claude/install.py
arzule_ingest/claude/normalize.py
arzule_ingest/claude/security.py
arzule_ingest/claude/session.py
arzule_ingest/claude/spanctx.py
arzule_ingest/claude/stream_sink.py
arzule_ingest/claude/transcript.py
arzule_ingest/claude/turn.py
arzule_ingest/claude/wrapper.py
arzule_ingest/crewai/__init__.py
arzule_ingest/crewai/handoff.py
arzule_ingest/crewai/hooks_llm.py
arzule_ingest/crewai/hooks_tool.py
arzule_ingest/crewai/implicit_handoff.py
arzule_ingest/crewai/install.py
arzule_ingest/crewai/listener.py
arzule_ingest/crewai/normalize.py
arzule_ingest/crewai/spanctx.py
arzule_ingest/langchain/__init__.py
arzule_ingest/langchain/callback_handler.py
arzule_ingest/langchain/handoff.py
arzule_ingest/langchain/install.py
arzule_ingest/langchain/normalize.py
arzule_ingest/langchain/spanctx.py
arzule_ingest/langgraph/__init__.py
arzule_ingest/langgraph/callback_handler.py
arzule_ingest/langgraph/install.py
arzule_ingest/langgraph/normalize.py
arzule_ingest/langgraph/spanctx.py
arzule_ingest/run_managers/__init__.py
arzule_ingest-0.9.2.dist-info/METADATA
arzule_ingest-0.9.2.dist-info/WHEEL
arzule_ingest-0.9.2.dist-info/entry_points.txt
arzule_ingest-0.9.2.dist-info/licenses/LICENSE
arzule_ingest-0.9.2.dist-info/RECORD
