Metadata-Version: 2.4
Name: arzule-ingest
Version: 0.9.2
Summary: Lightweight SDK for capturing multi-agent traces with self-hosting support
Project-URL: Homepage, https://arzule.com
Project-URL: Documentation, https://docs.arzule.com
Project-URL: Repository, https://github.com/arzule/arzule-ingest
Author: Arzule
License:                                  Apache License
License-File: LICENSE
Keywords: agents,autogen,crewai,langchain,langgraph,llm,multi-agent,observability,tracing
Classifier: Development Status :: 4 - Beta
Classifier: Intended Audience :: Developers
Classifier: Programming Language :: Python :: 3
Classifier: Programming Language :: Python :: 3.10
Classifier: Programming Language :: Python :: 3.11
Classifier: Programming Language :: Python :: 3.12
Classifier: Programming Language :: Python :: 3.13
Classifier: Programming Language :: Python :: 3.14
Classifier: Topic :: Software Development :: Libraries :: Python Modules
Classifier: Topic :: System :: Monitoring
Requires-Python: >=3.10
Requires-Dist: cryptography>=42.0.0
Requires-Dist: httpx>=0.27.0
Requires-Dist: pydantic>=2.0.0
Provides-Extra: all
Requires-Dist: crewai>=0.80.0; extra == 'all'
Requires-Dist: langchain-core>=0.2.0; extra == 'all'
Requires-Dist: langchain>=0.2.0; extra == 'all'
Requires-Dist: pyautogen<0.3.0,>=0.2.0; extra == 'all'
Provides-Extra: autogen
Requires-Dist: pyautogen<0.3.0,>=0.2.0; extra == 'autogen'
Provides-Extra: crewai
Requires-Dist: crewai>=0.80.0; extra == 'crewai'
Provides-Extra: dev
Requires-Dist: crewai>=0.80.0; extra == 'dev'
Requires-Dist: langchain-core>=0.2.0; extra == 'dev'
Requires-Dist: langchain-openai>=0.1.0; extra == 'dev'
Requires-Dist: langchain>=0.2.0; extra == 'dev'
Requires-Dist: pytest-asyncio>=0.23.0; extra == 'dev'
Requires-Dist: pytest>=8.0.0; extra == 'dev'
Provides-Extra: langchain
Requires-Dist: langchain-core>=0.2.0; extra == 'langchain'
Requires-Dist: langchain>=0.2.0; extra == 'langchain'
Provides-Extra: server
Requires-Dist: fastapi>=0.100.0; extra == 'server'
Requires-Dist: uvicorn>=0.30.0; extra == 'server'
